genhost/__init__.py
genhost/__main__.py
genhost/main.py
genhost-0.1.1.dist-info/METADATA
genhost-0.1.1.dist-info/WHEEL
genhost-0.1.1.dist-info/entry_points.txt
genhost-0.1.1.dist-info/RECORD
